nueramic_mathml/__init__.py
nueramic_mathml/calculus.py
nueramic_mathml/ml/__init__.py
nueramic_mathml/ml/classification.py
nueramic_mathml/ml/metrics.py
nueramic_mathml/ml/optimize.py
nueramic_mathml/ml/regression.py
nueramic_mathml/multi_optimize.py
nueramic_mathml/one_optimize.py
nueramic_mathml/support.py
nueramic_mathml/visualize/__init__.py
nueramic_mathml/visualize/ml_animation.py
nueramic_mathml/visualize/multi_animation.py
nueramic_mathml/visualize/one_animation.py
nueramic_mathml-0.75.2.dist-info/LICENSE
nueramic_mathml-0.75.2.dist-info/WHEEL
nueramic_mathml-0.75.2.dist-info/METADATA
nueramic_mathml-0.75.2.dist-info/RECORD
