Metadata-Version: 2.1
Name: nueramic-mathml
Version: 0.75.2
Summary: Math algorithms in ML on torch
Home-page: https://github.com/nueramic/mathml
License: MIT
Author: Victor Barbarich
Author-email: vktrbr@icloud.com
Requires-Python: >=3.7.1,<3.11
Classifier: License :: OSI Approved :: MIT License
Classifier: Operating System :: OS Independent
Classifier: Programming Language :: Python :: 3
Classifier: Programming Language :: Python :: 3.10
Classifier: Programming Language :: Python :: 3.8
Classifier: Programming Language :: Python :: 3.9
Requires-Dist: numpy (>=1.21.6,<2.0.0)
Requires-Dist: pandas (>=1.3,<2.0)
Requires-Dist: plotly (>=5.8.2,<6.0.0)
Requires-Dist: scikit-learn (>=1.0,<2.0)
Requires-Dist: torch (>=1.11.0,<2.0.0)
Project-URL: Bug Tracker, https://github.com/nueramic/mathml/issues
Project-URL: Repository, https://github.com/nueramic/mathml
